canlabs/__init__.py
canlabs/can_interface_dtc.py
canlabs/can_interface_manager.py
canlabs/devices/__init__.py
canlabs/devices/usb2can.py
canlabs/utils/__init__.py
canlabs/utils/check_root.py
canlabs/utils/colors.py
CanLabs-0.1.2.37.dist-info/LICENSE
CanLabs-0.1.2.37.dist-info/METADATA
CanLabs-0.1.2.37.dist-info/WHEEL
CanLabs-0.1.2.37.dist-info/top_level.txt
CanLabs-0.1.2.37.dist-info/RECORD
