Metadata-Version: 2.1
Name: CanLabs
Version: 0.1.2.37
Summary: Gestion de l'interface CAN avec Python
Home-page: https://github.com/alexandre-meline/CanLabs
Author: Alexandre Meline
Author-email: alexandre.meline.dev@gmail.com
License: UNKNOWN
Platform: UNKNOWN
Classifier: Development Status :: 4 - Beta
Classifier: Intended Audience :: Developers
Classifier: License :: OSI Approved :: MIT License
Classifier: Programming Language :: Python :: 3
Classifier: Programming Language :: Python :: 3 :: Only
Classifier: Programming Language :: Python :: 3.8
Classifier: Programming Language :: Python :: 3.9
Classifier: Programming Language :: Python :: 3.10
Classifier: Programming Language :: Python :: 3.11
